danoliterate/__init__.py
danoliterate/__main__.py
danoliterate/configs/master.yaml
danoliterate/configs/databuild/citizenship_test.yaml
danoliterate/configs/databuild/da_cloze_self_test.yaml
danoliterate/configs/databuild/da_gym_2000.yaml
danoliterate/configs/databuild/hashtag_twitterhjerne.yaml
danoliterate/configs/databuild/hyggeswag.yaml
danoliterate/configs/databuild/nordjylland_news.yaml
danoliterate/configs/databuild/prompt_answer.yaml
danoliterate/configs/model/baseline.yaml
danoliterate/configs/model/claude-haiku.yaml
danoliterate/configs/model/claude-opus.yaml
danoliterate/configs/model/claude-sonnet.yaml
danoliterate/configs/model/danoliterate-baseline.yaml
danoliterate/configs/model/danoliterate-llama.yaml
danoliterate/configs/model/danoliterate-mistral.yaml
danoliterate/configs/model/danskgpt-api.yaml
danoliterate/configs/model/danskgpt-tiny-chat.yaml
danoliterate/configs/model/danskgpt-tiny.yaml
danoliterate/configs/model/danskgpt.yaml
danoliterate/configs/model/gemma-7b-it.yaml
danoliterate/configs/model/gemma-7b.yaml
danoliterate/configs/model/google-gemini-pro.yaml
danoliterate/configs/model/gpt-7b-nordic-prerelease.yaml
danoliterate/configs/model/gpt-neo-da.yaml
danoliterate/configs/model/gpt-neox-da.yaml
danoliterate/configs/model/gpt-sw3-20b-instruct.yaml
danoliterate/configs/model/gpt-sw3-20b.yaml
danoliterate/configs/model/gpt-sw3-6b-instruct.yaml
danoliterate/configs/model/gpt-sw3-6b.yaml
danoliterate/configs/model/heidrun-mistral-7b-base.yaml
danoliterate/configs/model/heidrun-mistral-7b-chat.yaml
danoliterate/configs/model/hestenet-lm.yaml
danoliterate/configs/model/kanelsnegl.yaml
danoliterate/configs/model/llama2-13b-chat.yaml
danoliterate/configs/model/llama2-13b.yaml
danoliterate/configs/model/llama2-70b-chat.yaml
danoliterate/configs/model/llama2-70b.yaml
danoliterate/configs/model/llama2-7b-chat.yaml
danoliterate/configs/model/llama2-7b.yaml
danoliterate/configs/model/mgpt-13b.yaml
danoliterate/configs/model/mgpt.yaml
danoliterate-0.1.0.dist-info/METADATA
danoliterate-0.1.0.dist-info/WHEEL
danoliterate-0.1.0.dist-info/top_level.txt
danoliterate-0.1.0.dist-info/RECORD
