Metadata-Version: 2.1
Name: danoliterate
Version: 0.1.0
Summary: Benchmark of Generative Large Language Models in Danish
Home-page: https://github.com/sorenmulli/danoliterate
Author: Søren Winkel Holm
Author-email: swholm@protonmail.com
License: Apache License 2.0
Requires-Dist: pandas ~=1.5.3
Requires-Dist: datasets ~=2.14.5
Requires-Dist: transformers ~=4.36.1
Requires-Dist: torch ~=2.1.1
Requires-Dist: safetensors ~=0.3.3
Requires-Dist: matplotlib ~=3.8.0
Requires-Dist: simple-term-menu ~=1.6.1
Requires-Dist: augmenty ~=1.4.4
Requires-Dist: seqeval ~=1.2.2
Requires-Dist: levenshtein ~=0.23.0
Requires-Dist: nltk ~=3.8.1
Requires-Dist: absl-py ~=2.1.0
Requires-Dist: evaluate ~=0.4.0
Requires-Dist: rouge-score ~=0.1.2
Requires-Dist: bert-score ~=0.3.13
Requires-Dist: scipy ~=1.12.0
Requires-Dist: gensim ~=4.3.2
Requires-Dist: danlp ~=0.1.2
Requires-Dist: huggingface-hub ~=0.19.4
Requires-Dist: hydra-core ~=1.3.2
Requires-Dist: hydra-colorlog ~=1.2.0
Requires-Dist: omegaconf ~=2.3.0
Requires-Dist: gitpython ~=3.1.37
Requires-Dist: black ~=23.7.0
Requires-Dist: isort ~=5.12.0
Requires-Dist: mypy ~=1.5.1
Requires-Dist: pylint ~=2.17.5
Requires-Dist: pandas-stubs ~=2.0.3
Requires-Dist: types-tqdm ~=4.66.0
Requires-Dist: types-requests ~=2.31.0
Provides-Extra: full
Requires-Dist: pypdf ~=3.16.1 ; extra == 'full'
Requires-Dist: fasttext-wheel ~=0.9.2 ; extra == 'full'
Requires-Dist: peft ~=0.5.0 ; extra == 'full'
Requires-Dist: spacy ~=3.5.4 ; extra == 'full'
Requires-Dist: beautifulsoup4 ~=4.12.2 ; extra == 'full'
Requires-Dist: trl ~=0.7.4 ; extra == 'full'
Requires-Dist: wandb ~=0.16.6 ; extra == 'full'
Requires-Dist: deepspeed ~=0.12.4 ; extra == 'full'
Requires-Dist: sentencepiece ~=0.1.99 ; extra == 'full'
Requires-Dist: accelerate ~=0.23.0 ; extra == 'full'
Requires-Dist: google-cloud-aiplatform ~=1.38.1 ; extra == 'full'
Requires-Dist: openai ~=0.28.1 ; extra == 'full'
Requires-Dist: anthropic ~=0.21.3 ; extra == 'full'
Requires-Dist: groq ==0.4.2 ; extra == 'full'
